Workbook

Sheet H90166
A1: PURCHASE ORDER
G2: PO NO: | H2: H90166
G3: PO DATE: | H3: 45842
A4: BUYER: MOONPO DEVELOPMENT(VIETNAM) LIMITED
B5: ADDRESS: LOT CN-01，DONG VAN IV INDUSTRIAL ZONE,LE HO WARD,NINH BINH PROVINCE, VIET NAM
B6: TAX NUMBER: 0700834811
B7: ATTN;Tina
A8: SELLER: TECHSEN ELECTRONICS(SHENZHEN) CO., LTD
B9: ADDRESS: NO.28 XIANGXING ROAD,BUYONG COMMUNITY,SHAJING STREET,BAO'AN DISTRICT,SHENZHEN CITY,CHINA.
A10: I. DESCRIPTIONS OF GOODS:Refer list
A11: NO | B11: DESCRIPTION OF GOODS | E11: QUANTITY | F11: UNIT | G11: ORIGIN | H11: UNIT PRICE (USD) | I11: AMOUNT (USD)
B12: Part no | C12: Line No. | D12: DESCR
A13: 1 | B13: GX-1F30 | C13: 1 | D13: PCBA BOARD MOUNTED LCD TRAY FIXTURE | E13: 1 | F13: PCS | G13: CHINA | H13: 6.0124 | I13: =H13*E13 -> 6.0124
A14: 2 | B14: GX-1F31 | C14: 2 | D14: LOCK VR NUT FIXTURE | E14: 1 | F14: PCS | G14: CHINA | H14: 5.3443 | I14: =H14*E14 -> 5.3443
A15: 3 | B15: GX-1F32 | C15: 3 | D15: LOCK VR NUT FIXTURE | E15: 1 | F15: PCS | G15: CHINA | H15: 5.6115 | I15: =H15*E15 -> 5.6115
A16: TOTAL: | E16: =SUM(E13:E15) -> 3 | I16: =SUM(I13:I15) -> 16.9682
A17: II. CONDITIONS AND TRADE TERMS:
B18: 1. Cargo is new 100%.
B19: 2. Delivery terms: CPT NOIBAI
B20: 3. Delivery time: in JUL
B21: 4. Shipping method: BY AIR
B22: 5. Packing standards: Following exporting standards
B23: 6. Payment terms: No Payment
B24: 7. PO has been acknowledged and signed by 02 parties and sent via email.
A25: ACCEPTED BY SELLER | F25: BUYER

Sheet Invoice 
A1: COMMERCIAL INVOICE
A2: SELLER: | J2: INVOICE NO:TS250017
B3: NAME: TECHSEN ELECTRONICS(SHENZHEN) CO., LTD | J3: INVOICE DATE:2025-07-04
B4: ADDRESS: NO.28 XIANGXING ROAD,BUYONG COMMUNITY,SHAJING STREET,BAO'AN DISTRICT,SHENZHEN CITY,CHINA. | J4: PO NO:below list
B5: TELL: +86 755 29698989 | J5: PAYMENT TERMS: NO PAYMENT
A6: BUYER: | J6: DELIVERY TERMS: CPT NOIBAI
B7: NAME: MOONPO DEVELOPMENT(VIETNAM) LIMITED | J7: PORT OF LOADING: SHENZHEN
B8: ADDRESS: LOT CN-01，DONG VAN IV INDUSTRIAL ZONE,LE HO WARD,NINH BINH PROVINCE, VIET NAM | J8: PORT OF DISCHARGE: NOIBAI
J9: PORT OF TRANSIT:
B10: TAX NUMBER: 0700834811 | J10: ETD POL:2025-07-04
B11: TELL:+84 9885 16638, Email: ltlien@moonpo.com | J11: ETA POD:2025-07-08
A12: VESSEL/VOYAGE: BY AIR
A13: NO | B13: DESCRIPTIONS OF GOODS | G13: HS CODE | H13: ORIGIN OF GOODS | I13: QUANTITY | J13: UNIT | K13: UNIT PRICE (USD) | L13: AMOUNT (USD)
B14: PO NO. | C14: PO Line No. | D14: PART NO | E14: CN NAME | F14: DESCR
A15: 1 | B15: H90166 | C15: 1 | D15: GX-1F30 | E15: PCBA装LCD托盘治具 | F15: PCBA BOARD MOUNTED LCD TRAY FIXTURE | G15: 84662090 | H15: CHINA | I15: 1 | J15: PCS | K15: 6.0124 | L15: =K15*I15 -> 6.0124
A16: 2 | B16: H90166 | C16: 2 | D16: GX-1F31 | E16: 锁VR螺母治具 | F16: LOCK VR NUT FIXTURE | G16: 84662090 | H16: CHINA | I16: 1 | J16: PCS | K16: 5.3443 | L16: =K16*I16 -> 5.3443
A17: 3 | B17: H90166 | C17: 3 | D17: GX-1F32 | E17: 装LCD贴棉治具 | F17: LOCK VR NUT FIXTURE | G17: 84662090 | H17: CHINA | I17: 1 | J17: PCS | K17: 5.6115 | L17: =K17*I17 -> 5.6115
A18: TOTAL: | I18: =SUM(I15:I17) -> 3 | L18: =SUM(L15:L17) -> 16.9682
K20: MOONPO DEVELOPMENT LIMITED

Sheet Packing list 
A1: PACKING LIST
A2: SELLER: | I2: ='Invoice '!J2 -> INVOICE NO:TS250017
B3: ='Invoice '!B3 -> NAME: TECHSEN ELECTRONICS(SHENZHEN) CO., LTD | I3: ='Invoice '!J3 -> INVOICE DATE:2025-07-04
B4: ='Invoice '!B4 -> ADDRESS: NO.28 XIANGXING ROAD,BUYONG COMMUNITY,SHAJING STREET,BAO'AN DISTRICT,SHENZHEN CITY,CHINA. | I4: ='Invoice '!J4 -> PO NO:below list
B5: ='Invoice '!B5 -> TELL: +86 755 29698989 | I5: ='Invoice '!J6 -> DELIVERY TERMS: CPT NOIBAI
A6: BUYER: | I6: ='Invoice '!J7 -> PORT OF LOADING: SHENZHEN
B7: ='Invoice '!B7 -> NAME: MOONPO DEVELOPMENT(VIETNAM) LIMITED | I7: ='Invoice '!J8 -> PORT OF DISCHARGE: NOIBAI
B8: ='Invoice '!B8 -> ADDRESS: LOT CN-01，DONG VAN IV INDUSTRIAL ZONE,LE HO WARD,NINH BINH PROVINCE, VIET NAM | I8: ='Invoice '!J9 -> PORT OF TRANSIT:
I9: ='Invoice '!J10 -> ETD POL:2025-07-04
B10: ='Invoice '!B10 -> TAX NUMBER: 0700834811 | I10: ='Invoice '!J11 -> ETA POD:2025-07-08
B11: ='Invoice '!B11 -> TELL:+84 9885 16638, Email: ltlien@moonpo.com
A12: VESSEL/VOYAGE: BY AIR
A13: NO | B13: DESCRIPTIONS OF GOODS | F13: QUANTITY OF GOODS | G13: UNIT | H13: PALLET | I13: NO OF CARTON | J13: N/W (KG) | K13: G/W (KG) | L13: M3
B14: PO NO. | C14: PO Line No. | D14: PART NO. | E14: DESCR
A15: 1 | B15: H90166 | C15: 1 | D15: GX-1F30 | E15: PCBA BOARD MOUNTED LCD TRAY FIXTURE | F15: 1 | G15: PCS | H15: / | I15: A01 | J15: 0.47 | K15: 2.37
A16: 2 | B16: H90166 | C16: 2 | D16: GX-1F31 | E16: LOCK VR NUT FIXTURE | F16: 1 | G16: PCS | H16: / | I16: A01 | J16: 0.8 | K16: 0
A17: 3 | B17: H90166 | C17: 3 | D17: GX-1F32 | E17: LOCK VR NUT FIXTURE | F17: 1 | G17: PCS | H17: / | I17: A01 | J17: 0.77 | K17: 0
A18: TOTAL: | F18: =SUM(F15:F17) -> 3 | J18: =SUM(J15:J17) -> 2.04 | K18: =SUM(K15:K17) -> 2.37
A19: NO OF PACKAGE: 1 PACKAGE ONLY
F20: MOONPO DEVELOPMENT LIMITED
