Workbook

Sheet H90131
A1: PURCHASE ORDER
G2: PO NO: | H2: H90131
G3: PO DATE: | H3: 45593
A4: BUYER: MOONPO DEVELOPMENT(VIETNAM) LIMITED
B5: ADDRESS: LOT CN-01, DONG VAN IV INDUSTRIAL ZONE, DAI CUONG COMMUNE, KIM BANG DISTRICT, HA NAM PROVINCE, VIETNAM
B6: TAX NUMBER: 0700834811
B7: ATTN;Lina
A8: SELLER: MOONPO DEVELOPMENT LIMITED
B9: ADDRESS: FLAT 4-7, 1/F, WAH YIU INDUSTRIAL CENTRE, 30-32 AU PUI WAN STREET, FO TAN, SHATIN, N.T, HONGKONG
A10: I. DESCRIPTIONS OF GOODS:Refer list
A11: NO | B11: DESCRIPTION OF GOODS | E11: QUANTITY | F11: UNIT | G11: ORIGIN | H11: UNIT PRICE (USD) | I11: AMOUNT (USD)
B12: Part no | C12: Line No. | D12: DESCR
A13: 1 | B13: WSID-10034 | C13: 1 | D13: FOOT CLIPPER STAND | E13: 2 | F13: PCS | G13: CHINA | H13: 10 | I13: =H13*E13 -> 20
A14: TOTAL: | E14: =SUM(E13:E13) -> 2 | I14: =SUM(I13:I13) -> 20
A15: II. CONDITIONS AND TRADE TERMS:
B16: 1. Cargo is new 100%.
B17: 2. Delivery terms: CPT NOIBAI
B18: 3. Delivery time: in NOVC,2024
B19: 4. Shipping method: BY AIR
B20: 5. Packing standards: Following exporting standards
B21: 6. Payment terms: No Payment
B22: 7. PO has been acknowledged and signed by 02 parties and sent via email.
A23: ACCEPTED BY SELLER | F23: BUYER

Sheet Invoice 
A1: COMMERCIAL INVOICE
A2: SELLER: | J2: INVOICE NO:MDL240034
B3: NAME: MOONPO DEVELOPMENT LIMITED | J3: INVOICE DATE:2024-10-28
B4: ADDRESS: FLAT 4-7, 1/F, WAH YIU INDUSTRIAL CENTRE, 30-32 AU PUI WAN STREET, FO TAN, SHATIN, N.T, HONGKONG | J4: PO NO:below list
B5: TELL: +852-26888777 | J5: PAYMENT TERMS: NO PAYMENT
A6: BUYER: | J6: DELIVERY TERMS: CPT NOIBAI
B7: NAME: MOONPO DEVELOPMENT(VIETNAM) LIMITED | J7: PORT OF LOADING: SHENZHEN
B8: ADDRESS: LOT CN-01, DONG VAN IV INDUSTRIAL ZONE, DAI CUONG COMMUNE, KIM BANG DISTRICT, HA NAM PROVINCE, VIETNAM | J8: PORT OF DISCHARGE: NOIBAI
J9: PORT OF TRANSIT:
B10: TAX NUMBER: 0700834811 | J10: ETD POL:2024-10-28
B11: TELL:+84 904 923 783, Email: vttdung@moonpo.com | J11: ETA POD:2024-11-01
A12: VESSEL/VOYAGE: BY AIR
A13: NO | B13: DESCRIPTIONS OF GOODS | G13: HS CODE | H13: ORIGIN OF GOODS | I13: QUANTITY | J13: UNIT | K13: UNIT PRICE (USD) | L13: AMOUNT (USD)
B14: PO NO. | C14: PO Line No. | D14: PART NO | E14: CN NAME | F14: DESCR
A15: 1 | B15: H90131 | C15: 1 | D15: WSID-10034 | E15: 剪角器座 | F15: FOOT CLIPPER STAND | G15: 39269099 | H15: CHINA | I15: 2 | J15: PCS | K15: 10 | L15: =K15*I15 -> 20
A16: TOTAL: | I16: =SUM(I15:I15) -> 2 | L16: =SUM(L15:L15) -> 20
K18: MOONPO DEVELOPMENT LIMITED

Sheet Packing list 
A1: PACKING LIST
A2: SELLER: | I2: ='Invoice '!J2 -> INVOICE NO:MDL240034
B3: ='Invoice '!B3 -> NAME: MOONPO DEVELOPMENT LIMITED | I3: ='Invoice '!J3 -> INVOICE DATE:2024-10-28
B4: ='Invoice '!B4 -> ADDRESS: FLAT 4-7, 1/F, WAH YIU INDUSTRIAL CENTRE, 30-32 AU PUI WAN STREET, FO TAN, SHATIN, N.T, HONGKONG | I4: ='Invoice '!J4 -> PO NO:below list
B5: ='Invoice '!B5 -> TELL: +852-26888777 | I5: ='Invoice '!J6 -> DELIVERY TERMS: CPT NOIBAI
A6: BUYER: | I6: ='Invoice '!J7 -> PORT OF LOADING: SHENZHEN
B7: ='Invoice '!B7 -> NAME: MOONPO DEVELOPMENT(VIETNAM) LIMITED | I7: ='Invoice '!J8 -> PORT OF DISCHARGE: NOIBAI
B8: ='Invoice '!B8 -> ADDRESS: LOT CN-01, DONG VAN IV INDUSTRIAL ZONE, DAI CUONG COMMUNE, KIM BANG DISTRICT, HA NAM PROVINCE, VIETNAM | I8: ='Invoice '!J9 -> PORT OF TRANSIT:
I9: ='Invoice '!J10 -> ETD POL:2024-10-28
B10: ='Invoice '!B10 -> TAX NUMBER: 0700834811 | I10: ='Invoice '!J11 -> ETA POD:2024-11-01
B11: ='Invoice '!B11 -> TELL:+84 904 923 783, Email: vttdung@moonpo.com
A12: VESSEL/VOYAGE: BY AIR
A13: NO | B13: DESCRIPTIONS OF GOODS | F13: QUANTITY OF GOODS | G13: UNIT | H13: PALLET | I13: NO OF CARTON | J13: N/W (KG) | K13: G/W (KG) | L13: M3
B14: PO NO. | C14: PO Line No. | D14: PART NO. | E14: DESCR
A15: 1 | B15: H90131 | C15: 1 | D15: WSID-10034 | E15: FOOT CLIPPER STAND | F15: 2 | G15: PCS | H15: / | I15: / | J15: 0.2 | K15: 0.3
A16: TOTAL: | F16: =SUM(F15:F15) -> 2 | J16: =SUM(J15:J15) -> 0.2 | K16: =SUM(K15:K15) -> 0.3
A17: NO OF PACKAGE: 1 PACKAGE ONLY
F18: MOONPO TRADING(SHENZHEN)CO.,LTD
