Workbook

Sheet 250611-1117
A1: PURCHASE ORDER
E2: PO NO:250611-1117
E3: PO DATE: | F3: 45869
A4: BUYER: | B4: MOONPO DEVELOPMENT(VIETNAM) LIMITED
B5: ADDRESS: LOT CN-01，DONG VAN IV INDUSTRIAL ZONE,LE HO WARD,NINH BINH PROVINCE, VIET NAM
B6: TAX NO: 0700834811
B7: PIC: MR. YC WONG
A8: SELLER: | B8: MOONPO TRADING(SHENZHEN)CO.,LTD
B9: ADDRESS: 1F,NO.28 XIANGXING ROAD,BUYONG COMMUNITY,SHAJING STREET,BAO'AN DISTRICT,SHENZHEN CITY,CHINA.
A10: I. DESCRIPTIONS OF GOODS:BY OCEAN
A11: NO | B11: DESCRIPTION OF GOODS | D11: QUANTITY | E11: UNIT | F11: ORIGIN | G11: UNIT PRICE (USD) | H11: AMOUNT (USD)
B12: Part no | C12: DESC
A13: 1 | B13: SPY-SP-21008-01 | C13: STEEI PLATE | D13: 28 | E13: PCS | F13: CHINA | G13: 14.3428 | H13: =G13*D13 -> 401.5984
A14: 2 | B14: SPY-Film-21008-01 | C14: FILM | D14: 10 | E14: PCS | F14: CHINA | G14: 2.2647 | H14: =G14*D14 -> 22.647
D15: =SUM(D13:D14) -> 38 | H15: =SUM(H13:H14) -> 424.2454
B17: 1. Cargo is new 100%.
B18: 2. Delivery terms: C&F HAIPHONG
B19: 3. Delivery time: in JUL,2025
B20: 4. Shipping method: BY OCEAN
B21: 5. Packing standards: Following exporting standards
B22: 6. Payment terms: TT
B23: 7. PO has been acknowledged and signed by 02 parties and sent via email.
A24: ACCEPTED BY SELLER | E24: BUYER

Sheet 250627-1115
A1: PURCHASE ORDER
E2: PO NO:250627-1115
E3: PO DATE: | F3: 45866
A4: BUYER: | B4: MOONPO DEVELOPMENT(VIETNAM) LIMITED
B5: ADDRESS: LOT CN-01，DONG VAN IV INDUSTRIAL ZONE,LE HO WARD,NINH BINH PROVINCE, VIET NAM
B6: TAX NO: 0700834811
B7: PIC: MR. YC WONG
A8: SELLER: | B8: MOONPO TRADING(SHENZHEN)CO.,LTD
B9: ADDRESS: 1F,NO.28 XIANGXING ROAD,BUYONG COMMUNITY,SHAJING STREET,BAO'AN DISTRICT,SHENZHEN CITY,CHINA.
A10: I. DESCRIPTIONS OF GOODS:BY OCEAN
A11: NO | B11: DESCRIPTION OF GOODS | D11: QUANTITY | E11: UNIT | F11: ORIGIN | G11: UNIT PRICE (USD) | H11: AMOUNT (USD)
B12: Part no | C12: DESC
A13: 1 | B13: BOPEXTMF01A | C13: WAVE SOLDERING FIXTURE | D13: 12 | E13: PCS | F13: CHINA | G13: 49.7022 | H13: =G13*D13 -> 596.4264
A14: 2 | B14: BOPEXTSF01A | C14: WAVE SOLDERING FIXTURE | D14: 4 | E14: PCS | F14: CHINA | G14: 49.7022 | H14: =G14*D14 -> 198.8088
A15: 3 | B15: BOPEXTKF01A | C15: WAVE SOLDERING FIXTURE | D15: 2 | E15: PCS | F15: CHINA | G15: 49.7022 | H15: =G15*D15 -> 99.4044
A16: 4 | B16: BOPMICF01A | C16: WAVE SOLDERING FIXTURE | D16: 8 | E16: PCS | F16: CHINA | G16: 49.7022 | H16: =G16*D16 -> 397.6176
A17: 5 | B17: BOPMICF02A | C17: WAVE SOLDERING FIXTURE | D17: 4 | E17: PCS | F17: CHINA | G17: 49.7022 | H17: =G17*D17 -> 198.8088
A18: 6 | B18: BOPMICF03A | C18: WAVE SOLDERING FIXTURE | D18: 8 | E18: PCS | F18: CHINA | G18: 15.0977 | H18: =G18*D18 -> 120.7816
A19: 7 | B19: EXTREME(21008) | C19: ULTRASONIC MOLD | D19: 1 | E19: SET | F19: CHINA | G19: 200.4122 | H19: =G19*D19 -> 200.4122
D20: =SUM(D13:D19) -> 39 | H20: =SUM(H13:H19) -> 1812.2598
B22: 1. Cargo is new 100%.
B23: 2. Delivery terms: C&F HAIPHONG
B24: 3. Delivery time: in JUL,2025
B25: 4. Shipping method: BY OCEAN
B26: 5. Packing standards: Following exporting standards
B27: 6. Payment terms: TT
B28: 7. PO has been acknowledged and signed by 02 parties and sent via email.
A29: ACCEPTED BY SELLER | E29: BUYER

Sheet 250637-1117
A1: PURCHASE ORDER
E2: PO NO:250637-1117
E3: PO DATE: | F3: 45869
A4: BUYER: | B4: MOONPO DEVELOPMENT(VIETNAM) LIMITED
B5: ADDRESS: LOT CN-01，DONG VAN IV INDUSTRIAL ZONE,LE HO WARD,NINH BINH PROVINCE, VIET NAM
B6: TAX NO: 0700834811
B7: PIC: MR. YC WONG
A8: SELLER: | B8: MOONPO TRADING(SHENZHEN)CO.,LTD
B9: ADDRESS: 1F,NO.28 XIANGXING ROAD,BUYONG COMMUNITY,SHAJING STREET,BAO'AN DISTRICT,SHENZHEN CITY,CHINA.
A10: I. DESCRIPTIONS OF GOODS:BY OCEAN
A11: NO | B11: DESCRIPTION OF GOODS | D11: QUANTITY | E11: UNIT | F11: ORIGIN | G11: UNIT PRICE (USD) | H11: AMOUNT (USD)
B12: Part no | C12: DESC
A13: 1 | B13: SPY-Rubber tip01-21008-01 | C13: RUBBER TIP | D13: 10 | E13: PCS | F13: CHINA | G13: 40.4619 | H13: =G13*D13 -> 404.619
A14: 2 | B14: SPY-Rubber tip02-21008-02 | C14: RUBBER TIP | D14: 30 | E14: PCS | F14: CHINA | G14: 19.3251 | H14: =G14*D14 -> 579.753
D15: =SUM(D13:D14) -> 40 | H15: =SUM(H13:H14) -> 984.372
B17: 1. Cargo is new 100%.
B18: 2. Delivery terms: C&F HAIPHONG
B19: 3. Delivery time: in JUL,2025
B20: 4. Shipping method: BY OCEAN
B21: 5. Packing standards: Following exporting standards
B22: 6. Payment terms: TT
B23: 7. PO has been acknowledged and signed by 02 parties and sent via email.
A24: ACCEPTED BY SELLER | E24: BUYER

Sheet 250648-1117
A1: PURCHASE ORDER
E2: PO NO:250648-1117
E3: PO DATE: | F3: 45863
A4: BUYER: | B4: MOONPO DEVELOPMENT(VIETNAM) LIMITED
B5: ADDRESS: LOT CN-01，DONG VAN IV INDUSTRIAL ZONE,LE HO WARD,NINH BINH PROVINCE, VIET NAM
B6: TAX NO: 0700834811
B7: PIC: MR. YC WONG
A8: SELLER: | B8: MOONPO TRADING(SHENZHEN)CO.,LTD
B9: ADDRESS: 1F,NO.28 XIANGXING ROAD,BUYONG COMMUNITY,SHAJING STREET,BAO'AN DISTRICT,SHENZHEN CITY,CHINA.
A10: I. DESCRIPTIONS OF GOODS:BY OCEAN
A11: NO | B11: DESCRIPTION OF GOODS | D11: QUANTITY | E11: UNIT | F11: ORIGIN | G11: UNIT PRICE (USD) | H11: AMOUNT (USD)
B12: Part no | C12: DESC
A13: 1 | B13: SPY-FIXTURE1-21008-01 | C13: FIXTURE | D13: 4 | E13: PCS | F13: CHINA | G13: 13.3608 | H13: =G13*D13 -> 53.4432
A14: 2 | B14: SPY-FIXTURE2-21008-02 | C14: FIXTURE | D14: 4 | E14: PCS | F14: CHINA | G14: 3.3402 | H14: =G14*D14 -> 13.3608
A15: 3 | B15: SPY-21008-01 | C15: SPRAY PAINTING MASK | D15: 14 | E15: PCS | F15: CHINA | G15: 264.544 | H15: =G15*D15 -> 3703.616
D16: =SUM(D13:D15) -> 22 | H16: =SUM(H13:H15) -> 3770.42
B18: 1. Cargo is new 100%.
B19: 2. Delivery terms: C&F HAIPHONG
B20: 3. Delivery time: in JUL,2025
B21: 4. Shipping method: BY OCEAN
B22: 5. Packing standards: Following exporting standards
B23: 6. Payment terms: TT
B24: 7. PO has been acknowledged and signed by 02 parties and sent via email.
A25: ACCEPTED BY SELLER | E25: BUYER

Sheet 250663-1115
A1: PURCHASE ORDER
E2: PO NO:250663-1115
E3: PO DATE: | F3: 45869
A4: BUYER: | B4: MOONPO DEVELOPMENT(VIETNAM) LIMITED
B5: ADDRESS: LOT CN-01，DONG VAN IV INDUSTRIAL ZONE,LE HO WARD,NINH BINH PROVINCE, VIET NAM
B6: TAX NO: 0700834811
B7: PIC: MR. YC WONG
A8: SELLER: | B8: MOONPO TRADING(SHENZHEN)CO.,LTD
B9: ADDRESS: 1F,NO.28 XIANGXING ROAD,BUYONG COMMUNITY,SHAJING STREET,BAO'AN DISTRICT,SHENZHEN CITY,CHINA.
A10: I. DESCRIPTIONS OF GOODS:BY OCEAN
A11: NO | B11: DESCRIPTION OF GOODS | D11: QUANTITY | E11: UNIT | F11: ORIGIN | G11: UNIT PRICE (USD) | H11: AMOUNT (USD)
B12: Part no | C12: DESC
A13: 1 | B13: BOPEXTR-F15 | C13: HIT THE HOST SCREW FIXTURE | D13: 2 | E13: PCS | F13: CHINA | G13: 13.3608 | H13: =G13*D13 -> 26.7216
A14: 2 | B14: BOPEXTR-F01 | C14: BLUE BUTTON CLAMP | D14: 1 | E14: PCS | F14: CHINA | G14: 8.0165 | H14: =G14*D14 -> 8.0165
A15: 3 | B15: BOPEXTR-F02 | C15: YELLOW BUTTON CLAMP | D15: 1 | E15: PCS | F15: CHINA | G15: 8.0165 | H15: =G15*D15 -> 8.0165
A16: 4 | B16: BOPEXTR-F03 | C16: GREEN BUTTON HANDLE CLAMP | D16: 1 | E16: PCS | F16: CHINA | G16: 8.0165 | H16: =G16*D16 -> 8.0165
A17: 5 | B17: BOPEXTR-F04 | C17: GREEN BUTTON CLAMP | D17: 1 | E17: PCS | F17: CHINA | G17: 6.6804 | H17: =G17*D17 -> 6.6804
A18: 6 | B18: BOPEXTR-F05 | C18: LARGE BUTTON CLAMP FOR DOUGH SHELLE | D18: 2 | E18: PCS | F18: CHINA | G18: 8.0165 | H18: =G18*D18 -> 16.033
A19: 7 | B19: BOPEXTR-F06 | C19: LARGE BUTTON CLAMP FOR BUTTOM SHELLE | D19: 2 | E19: PCS | F19: CHINA | G19: 8.0165 | H19: =G19*D19 -> 16.033
A20: 8 | B20: BOPEXTR-F07 | C20: HIT THE PCB BOARD AND BASKET BUTTON FIXTURE | D20: 2 | E20: PCS | F20: CHINA | G20: 8.0165 | H20: =G20*D20 -> 16.033
A21: 9 | B21: BOPEXTR-F08 | C21: INSTALL BUTTON HANDLE AND CYCLOID CLAMP | D21: 2 | E21: PCS | F21: CHINA | G21: 8.0165 | H21: =G21*D21 -> 16.033
A22: 10 | B22: BOPEXTR-F09 | C22: FIXTURE FOR ASSEMBLE NUT | D22: 1 | E22: PCS | F22: CHINA | G22: 5.3443 | H22: =G22*D22 -> 5.3443
A23: 11 | B23: BOPEXTR-F010 | C23: FIXTURE FOR PRESSURE BATTERY CONTACT PLATE | D23: 1 | E23: PCS | F23: CHINA | G23: 26.7216 | H23: =G23*D23 -> 26.7216
A24: 12 | B24: BOPEXTR-F11 | C24: FIXTURE FOR THE HORN COVER | D24: 1 | E24: PCS | F24: CHINA | G24: 8.0165 | H24: =G24*D24 -> 8.0165
... A50: 38 | B50: BOP-IT-MICRO | C50: STENCIL | D50: 1 | E50: PCS | F50: CHINA | G50: 19.3732 | H50: =G50*D50 -> 19.3732
D51: =SUM(D13:D50) -> 54 | H51: =SUM(H13:H50) -> 611.2571
B53: 1. Cargo is new 100%.
B54: 2. Delivery terms: C&F HAIPHONG
B55: 3. Delivery time: in JUL,2025
B56: 4. Shipping method: BY OCEAN
B57: 5. Packing standards: Following exporting standards
B58: 6. Payment terms: TT
B59: 7. PO has been acknowledged and signed by 02 parties and sent via email.
A60: ACCEPTED BY SELLER | E60: BUYER

Sheet Invoice 
A1: COMMERCIAL INVOICE
A2: SELLER: | J2: INVOICE NO:MPT250046
B3: NAME:MOONPO TRADING(SHENZHEN)CO.,LTD | J3: INVOICE DATE:2025-07-23
B4: ADDRESS: 1F,NO.28 XIANGXING ROAD,BUYONG COMMUNITY,SHAJING STREET,BAO'AN DISTRICT,SHENZHEN CITY,CHINA. | J4: PO NO：Below list
J5: PAYMENT TERMS: TT
B6: TELL: 0755-29698989 | J6: DELIVERY TERMS:C&F HAIPHONG
A7: BUYER: | J7: PORT OF LOADING:SHEKOU
B8: NAME: MOONPO DEVELOPMENT(VIETNAM) LIMITED | J8: PORT OF DISCHARGE: HAIPHONG
B9: ADDRESS: LOT CN-01，DONG VAN IV INDUSTRIAL ZONE,LE HO WARD,NINH BINH PROVINCE, VIET NAM | J9: PORT OF TRANSIT:
J10: ETD POL:2025-07-28
B11: TAX NUMBER: 0700834811 | J11: ETA POD:2025-07-31
B12: TELL:(+84) 9885 16638, Email: ltlien@moonpo.com
A13: VESSEL/VOYAGE: BY OCEAN
A14: NO | B14: DESCRIPTIONS OF GOODS | G14: HS code | H14: ORIGIN OF GOODS | I14: QUANTITY | J14: UNIT | K14: UNIT PRICE (USD) | L14: AMOUNT (USD)
B15: PO NO. | C15: PO Line No. | D15: PART NO | E15: NAME | F15: DESC
A16: 1 | B16: 250611-1117 | C16: 4/5 | D16: SPY-SP-21008-01 | E16: 钢板 | F16: STEEI PLATE | G16: 85013140 | H16: CHINA | I16: 28 | J16: PCS | K16: 14.3428 | L16: =K16*I16 -> 401.5984
A17: 2 | B17: 250648-1117 | C17: 1 | D17: SPY-FIXTURE1-21008-01 | E17: 夹具 | F17: FIXTURE | G17: 84662090 | H17: CHINA | I17: 4 | J17: PCS | K17: 13.3608 | L17: =K17*I17 -> 53.4432
A18: 3 | B18: 250648-1117 | C18: 2 | D18: SPY-FIXTURE2-21008-02 | E18: 夹具 | F18: FIXTURE | G18: 84662090 | H18: CHINA | I18: 4 | J18: PCS | K18: 3.3402 | L18: =K18*I18 -> 13.3608
A19: 4 | B19: 250611-1117 | C19: 2 | D19: SPY-Film-21008-01 | E19: 菲林 | F19: FILM | G19: 37013000 | H19: CHINA | I19: 10 | J19: PCS | K19: 2.2647 | L19: =K19*I19 -> 22.647
A20: 5 | B20: 250637-1117 | C20: 1 | D20: SPY-Rubber tip01-21008-01 | E20: 胶头 | F20: RUBBER TIP | G20: 39269099 | H20: CHINA | I20: 10 | J20: PCS | K20: 40.4619 | L20: =K20*I20 -> 404.619
A21: 6 | B21: 250637-1117 | C21: 2 | D21: SPY-Rubber tip02-21008-02 | E21: 胶头 | F21: RUBBER TIP | G21: 39269099 | H21: CHINA | I21: 30 | J21: PCS | K21: 19.3251 | L21: =K21*I21 -> 579.753
A22: 7 | B22: 250648-1117 | C22: 3 | D22: SPY-21008-01 | E22: 喷油模 | F22: SPRAY PAINTING MASK | G22: 84249099 | H22: CHINA | I22: 14 | J22: PCS | K22: 264.544 | L22: =K22*I22 -> 3703.616
A23: 8 | B23: 250627-1115 | C23: 5 | D23: BOPEXTMF01A | E23: 过炉治具 | F23: WAVE SOLDERING FIXTURE | G23: 84662090 | H23: CHINA | I23: 8 | J23: PCS | K23: 49.7022 | L23: =K23*I23 -> 397.6176
A24: 9 | B24: 250627-1115 | C24: 5 | D24: BOPEXTMF01A | E24: 过炉治具 | F24: WAVE SOLDERING FIXTURE | G24: 84662090 | H24: CHINA | I24: 4 | J24: PCS | K24: 49.7022 | L24: =K24*I24 -> 198.8088
A25: 10 | B25: 250627-1115 | C25: 7 | D25: BOPEXTSF01A | E25: 过炉治具 | F25: WAVE SOLDERING FIXTURE | G25: 84662090 | H25: CHINA | I25: 4 | J25: PCS | K25: 49.7022 | L25: =K25*I25 -> 198.8088
A26: 11 | B26: 250627-1115 | C26: 6 | D26: BOPEXTKF01A | E26: 过炉治具 | F26: WAVE SOLDERING FIXTURE | G26: 84662090 | H26: CHINA | I26: 2 | J26: PCS | K26: 49.7022 | L26: =K26*I26 -> 99.4044
A27: 12 | B27: 250627-1115 | C27: 2 | D27: BOPMICF01A | E27: 过炉治具 | F27: WAVE SOLDERING FIXTURE | G27: 84662090 | H27: CHINA | I27: 8 | J27: PCS | K27: 49.7022 | L27: =K27*I27 -> 397.6176
A28: 13 | B28: 250627-1115 | C28: 3 | D28: BOPMICF02A | E28: 过炉治具 | F28: WAVE SOLDERING FIXTURE | G28: 84662090 | H28: CHINA | I28: 4 | J28: PCS | K28: 49.7022 | L28: =K28*I28 -> 198.8088
... A68: 53 | B68: 250663-1115 | C68: 38 | D68: BOP-IT-MICRO | E68: 钢网 | F68: STENCIL | G68: 73144900 | H68: CHINA | I68: 1 | J68: PCS | K68: 19.3732 | L68: =K68*I68 -> 19.3732
A69: TOTAL: | I69: =SUM(I16:I68) -> 193 | L69: =SUM(L16:L68) -> 7602.5543
I71: MOONPO TRADING(SHENZHEN)CO.,LTD

Sheet Packing list 
A1: PACKING LIST
A2: SELLER: | H2: ='Invoice '!J2 -> INVOICE NO:MPT250046
B3: ='Invoice '!B3 -> NAME:MOONPO TRADING(SHENZHEN)CO.,LTD | H3: ='Invoice '!J3 -> INVOICE DATE:2025-07-23
B4: ADDRESS: 1F,NO.28 XIANGXING ROAD,BUYONG COMMUNITY,SHAJING STREET,BAO'AN DISTRICT,SHENZHEN CITY,CHINA. | H4: ='Invoice '!J4 -> PO NO：Below list
H5: ='Invoice '!J5 -> PAYMENT TERMS: TT
B6: ='Invoice '!B6 -> TELL: 0755-29698989 | H6: ='Invoice '!J6 -> DELIVERY TERMS:C&F HAIPHONG
A7: BUYER: | H7: ='Invoice '!J7 -> PORT OF LOADING:SHEKOU
B8: ='Invoice '!B8 -> NAME: MOONPO DEVELOPMENT(VIETNAM) LIMITED | H8: ='Invoice '!J8 -> PORT OF DISCHARGE: HAIPHONG
B9: ='Invoice '!B9 -> ADDRESS: LOT CN-01，DONG VAN IV INDUSTRIAL ZONE,LE HO WARD,NINH BINH PROVINCE, VIET NAM | H9: ='Invoice '!J9 -> PORT OF TRANSIT:
H10: ='Invoice '!J10 -> ETD POL:2025-07-28
B11: ='Invoice '!B11 -> TAX NUMBER: 0700834811 | H11: ='Invoice '!J11 -> ETA POD:2025-07-31
B12: ='Invoice '!B12 -> TELL:(+84) 9885 16638, Email: ltlien@moonpo.com
A13: VESSEL/VOYAGE: BY OCEAN
A14: NO | B14: DESCRIPTIONS OF GOODS | F14: QUANTITY OF GOODS | G14: UNIT | H14: NO OF CARTON | I14: G/W (KG) | J14: N/W (KG) | K14: M3
B15: PO NO. | C15: PO Line No. | D15: PART NO | E15: DESC
A16: 1 | B16: 250611-1117 | C16: 4/5 | D16: SPY-SP-21008-01 | E16: STEEI PLATE | F16: 28 | G16: PCS | H16: SPY02 | I16: 25.3 | J16: 21.56
A17: 2 | B17: 250648-1117 | C17: 1 | D17: SPY-FIXTURE1-21008-01 | E17: FIXTURE | F17: 4 | G17: PCS | H17: SPY02 | I17: 0 | J17: 2.38
A18: 3 | B18: 250648-1117 | C18: 2 | D18: SPY-FIXTURE2-21008-02 | E18: FIXTURE | F18: 4 | G18: PCS | H18: SPY02 | I18: 0 | J18: 0.33
A19: 4 | B19: 250611-1117 | C19: 2 | D19: SPY-Film-21008-01 | E19: FILM | F19: 10 | G19: PCS | H19: SPY02 | I19: 0 | J19: 0.02
B20: 250637-1117 | C20: 1 | D20: SPY-Rubber tip01-21008-01 | E20: RUBBER TIP | F20: 10 | G20: PCS | H20: SPY01 | I20: 6.5 | J20: 3.55
B21: 250637-1117 | C21: 2 | D21: SPY-Rubber tip02-21008-02 | E21: RUBBER TIP | F21: 30 | G21: PCS | H21: SPY01 | I21: 0 | J21: 2.7
B22: 250648-1117 | C22: 3 | D22: SPY-21008-01 | E22: SPRAY PAINTING MASK | F22: 14 | G22: PCS | H22: SPY03 | I22: 40 | J22: 30.52
B23: 250627-1115 | C23: 5 | D23: BOPEXTMF01A | E23: WAVE SOLDERING FIXTURE | F23: 8 | G23: PCS | H23: Q5 | I23: 12 | J23: 11.5
B24: 250627-1115 | C24: 5 | D24: BOPEXTMF01A | E24: WAVE SOLDERING FIXTURE | F24: 4 | G24: PCS | H24: Q6 | I24: 11.5 | J24: 6
B25: 250627-1115 | C25: 7 | D25: BOPEXTSF01A | E25: WAVE SOLDERING FIXTURE | F25: 4 | G25: PCS | H25: Q6 | I25: 0 | J25: 5
B26: 250627-1115 | C26: 6 | D26: BOPEXTKF01A | E26: WAVE SOLDERING FIXTURE | F26: 2 | G26: PCS | H26: Q7 | I26: 18.5 | J26: 2.4
B27: 250627-1115 | C27: 2 | D27: BOPMICF01A | E27: WAVE SOLDERING FIXTURE | F27: 8 | G27: PCS | H27: Q7 | I27: 0 | J27: 10.5
B28: 250627-1115 | C28: 3 | D28: BOPMICF02A | E28: WAVE SOLDERING FIXTURE | F28: 4 | G28: PCS | H28: Q7 | I28: 0 | J28: 3.6
B29: 250627-1115 | C29: 4 | D29: BOPMICF03A | E29: WAVE SOLDERING FIXTURE | F29: 8 | G29: PCS | H29: Q7 | I29: 0 | J29: 1.5
B30: 250627-1115 | C30: 1 | D30: EXTREME(21008) | E30: ULTRASONIC MOLD | F30: 1 | G30: SET | H30: Q8 | I30: 3 | J30: 2.32
B31: 250663-1115 | C31: 1 | D31: BOPEXTR-F15 | E31: HIT THE HOST SCREW FIXTURE | F31: 2 | G31: PCS | H31: Q1 | I31: 10.5 | J31: 9.81
... B68: 250663-1115 | C68: 38 | D68: BOP-IT-MICRO | E68: STENCIL | F68: 1 | G68: PCS | H68: Q4 | I68: 1.5 | J68: 0.6
A69: TOTAL: | F69: =SUM(F16:F68) -> 193 | I69: =SUM(I16:I68) -> 163.17 | J69: =SUM(J16:J68) -> 146.46
A70: NO OF PACKAGE: 11 PACKAGE ONLY
F71: MOONPO TRADING(SHENZHEN)CO.,LTD
