Workbook

Sheet 250302-1109
A1: PURCHASE ORDER
E2: PO NO:250302-1109
E3: PO DATE: | F3: 45757
A4: BUYER: | B4: MOONPO DEVELOPMENT(VIETNAM) LIMITED
B5: ADDRESS: LOT CN-01, DONG VAN IV INDUSTRIAL ZONE, DAI CUONG WARD, KIM BANG TOWN, HA NAM PROVINCE, VIET NAM.
B6: TAX NO: 0700834811
B7: PIC: MR. YC WONG
A8: SELLER: | B8: MOONPO TRADING(SHENZHEN)CO.,LTD
B9: ADDRESS: 1F,NO.28 XIANGXING ROAD,BUYONG COMMUNITY,SHAJING STREET,BAO'AN DISTRICT,SHENZHEN CITY,CHINA.
A10: I. DESCRIPTIONS OF GOODS:BY OCEAN
A11: NO | B11: DESCRIPTION OF GOODS | D11: QUANTITY | E11: UNIT | F11: ORIGIN | G11: UNIT PRICE (USD) | H11: AMOUNT (USD)
B12: Part no | C12: DESC
A13: 1 | B13: B125-6.5A | C13: PROTECTION FILM | D13: 100 | E13: ROLL | F13: CHINA | G13: 2.3969 | H13: =G13*D13 -> 239.69
D14: =SUM(D13:D13) -> 100 | H14: =SUM(H13:H13) -> 239.69
B16: 1. Cargo is new 100%.
B17: 2. Delivery terms: C&F HAIPHONG
B18: 3. Delivery time: in APR,2025
B19: 4. Shipping method: BY OCEAN
B20: 5. Packing standards: Following exporting standards
B21: 6. Payment terms: TT
B22: 7. PO has been acknowledged and signed by 02 parties and sent via email.
A23: ACCEPTED BY SELLER | E23: BUYER

Sheet 250340-1115
A1: PURCHASE ORDER
E2: PO NO:250340-1115
E3: PO DATE: | F3: 45770
A4: BUYER: | B4: MOONPO DEVELOPMENT(VIETNAM) LIMITED
B5: ADDRESS: LOT CN-01, DONG VAN IV INDUSTRIAL ZONE, DAI CUONG WARD, KIM BANG TOWN, HA NAM PROVINCE, VIET NAM.
B6: TAX NO: 0700834811
B7: PIC: MR. YC WONG
A8: SELLER: | B8: MOONPO TRADING(SHENZHEN)CO.,LTD
B9: ADDRESS: 1F,NO.28 XIANGXING ROAD,BUYONG COMMUNITY,SHAJING STREET,BAO'AN DISTRICT,SHENZHEN CITY,CHINA.
A10: I. DESCRIPTIONS OF GOODS:BY OCEAN
A11: NO | B11: DESCRIPTION OF GOODS | D11: QUANTITY | E11: UNIT | F11: ORIGIN | G11: UNIT PRICE (USD) | H11: AMOUNT (USD)
B12: Part no | C12: DESC
A13: 1 | B13: LT5GEO | C13: PCBA TESTING FIXTURE | D13: 1 | E13: PCS | F13: CHINA | G13: 39.9478 | H13: =G13*D13 -> 39.9478
A14: 2 | B14: AE-BRISA | C14: STICK BLOWING NOZZLE BOARD SPONGE FIXTURE | D14: 1 | E14: PCS | F14: CHINA | G14: 3.329 | H14: =G14*D14 -> 3.329
A15: 3 | B15: AE-BRISA | C15: FIXED NOZZLE ASSEMBLY RUBBER RING FIXTURE | D15: 1 | E15: PCS | F15: CHINA | G15: 2.9295 | H15: =G15*D15 -> 2.9295
A16: 4 | B16: AE-BRISA | C16: PRESSURE LEFT SHELL BEER MACHINE FIXTURE | D16: 1 | E16: PCS | F16: CHINA | G16: 10.6528 | H16: =G16*D16 -> 10.6528
A17: 5 | B17: AE-BRISA | C17: RIGHT SIDE SHELL BEER MACHINE FIXTURE | D17: 1 | E17: PCS | F17: CHINA | G17: 10.6528 | H17: =G17*D17 -> 10.6528
A18: 6 | B18: AE-BRISA | C18: BLOWING FIXTURE | D18: 1 | E18: PCS | F18: CHINA | G18: 113.1856 | H18: =G18*D18 -> 113.1856
D19: =SUM(D13:D18) -> 6 | H19: =SUM(H13:H18) -> 180.6975
B21: 1. Cargo is new 100%.
B22: 2. Delivery terms: C&F HAIPHONG
B23: 3. Delivery time: in APR,2025
B24: 4. Shipping method: BY OCEAN
B25: 5. Packing standards: Following exporting standards
B26: 6. Payment terms: TT
B27: 7. PO has been acknowledged and signed by 02 parties and sent via email.
A28: ACCEPTED BY SELLER | E28: BUYER

Sheet Invoice 
A1: COMMERCIAL INVOICE
A2: SELLER: | J2: INVOICE NO:MPT250016
B3: NAME:MOONPO TRADING(SHENZHEN)CO.,LTD | J3: INVOICE DATE:2025-04-23
B4: ADDRESS: 1F,NO.28 XIANGXING ROAD,BUYONG COMMUNITY,SHAJING STREET,BAO'AN DISTRICT,SHENZHEN CITY,CHINA. | J4: PO NO：Below list
J5: PAYMENT TERMS: TT
B6: TELL: 0755-29698989 | J6: DELIVERY TERMS:C&F HAIPHONG
A7: BUYER: | J7: PORT OF LOADING:SHEKOU
B8: NAME: MOONPO DEVELOPMENT(VIETNAM) LIMITED | J8: PORT OF DISCHARGE: HAIPHONG
B9: ADDRESS: LOT CN-01, DONG VAN IV INDUSTRIAL ZONE, DAI CUONG WARD, KIM BANG TOWN, HA NAM PROVINCE, VIET NAM | J9: PORT OF TRANSIT:
J10: ETD POL:2025-04-28
B11: TAX NUMBER: 0700834811 | J11: ETA POD:2025-04-30
B12: TELL:(+84) 0396869966, Email: vttdung@moonpo.com
A13: VESSEL/VOYAGE: BY OCEAN
A14: NO | B14: DESCRIPTIONS OF GOODS | G14: HS code | H14: ORIGIN OF GOODS | I14: QUANTITY | J14: UNIT | K14: UNIT PRICE (USD) | L14: AMOUNT (USD)
B15: PO NO. | C15: PO Line No. | D15: PART NO | E15: NAME | F15: DESC
A16: 1 | B16: 250302-1109 | C16: 1 | D16: B125-6.5A | E16: 保护膜 | F16: PROTECTION FILM | G16: 39191010 | H16: CHINA | I16: 100 | J16: ROLL | K16: 2.3969 | L16: =ROUND(K16*I16,4) -> 239.69
A17: 2 | B17: 250340-1115 | C17: 2 | D17: LT5GEO | E17: PCBA测试架治具 | F17: PCBA TESTING FIXTURE | G17: 90308410 | H17: CHINA | I17: 1 | J17: PCS | K17: 39.9478 | L17: =ROUND(K17*I17,4) -> 39.9478
A18: 3 | B18: 250340-1115 | C18: 3 | D18: AE-BRISA | E18: 贴吹嘴板海棉治具 | F18: STICK BLOWING NOZZLE BOARD SPONGE FIXTURE | G18: 84662090 | H18: CHINA | I18: 1 | J18: PCS | K18: 3.329 | L18: =ROUND(K18*I18,4) -> 3.329
A19: 4 | B19: 250340-1115 | C19: 4 | D19: AE-BRISA | E19: 固定吹嘴组件装胶圈治具 | F19: FIXED NOZZLE ASSEMBLY RUBBER RING FIXTURE | G19: 84662090 | H19: CHINA | I19: 1 | J19: PCS | K19: 2.9295 | L19: =ROUND(K19*I19,4) -> 2.9295
A20: 5 | B20: 250340-1115 | C20: 9 | D20: AE-BRISA | E20: 压左面壳啤机治具 | F20: PRESSURE LEFT SHELL BEER MACHINE FIXTURE | G20: 84662090 | H20: CHINA | I20: 1 | J20: PCS | K20: 10.6528 | L20: =ROUND(K20*I20,4) -> 10.6528
A21: 6 | B21: 250340-1115 | C21: 10 | D21: AE-BRISA | E21: 压右面壳啤机治具 | F21: RIGHT SIDE SHELL BEER MACHINE FIXTURE | G21: 84662090 | H21: CHINA | I21: 1 | J21: PCS | K21: 10.6528 | L21: =ROUND(K21*I21,4) -> 10.6528
A22: 7 | B22: 250340-1115 | C22: 11 | D22: AE-BRISA | E22: 吹气治具 | F22: BLOWING FIXTURE | G22: 84662090 | H22: CHINA | I22: 1 | J22: PCS | K22: 113.1856 | L22: =ROUND(K22*I22,4) -> 113.1856
A23: TOTAL: | I23: =SUM(I16:I22) -> 106 | L23: =SUM(L16:L22) -> 420.3875
I25: MOONPO TRADING(SHENZHEN)CO.,LTD

Sheet Packing list 
A1: PACKING LIST
A2: SELLER: | H2: ='Invoice '!J2 -> INVOICE NO:MPT250016
B3: ='Invoice '!B3 -> NAME:MOONPO TRADING(SHENZHEN)CO.,LTD | H3: ='Invoice '!J3 -> INVOICE DATE:2025-04-23
B4: ADDRESS: 1F,NO.28 XIANGXING ROAD,BUYONG COMMUNITY,SHAJING STREET,BAO'AN DISTRICT,SHENZHEN CITY,CHINA. | H4: ='Invoice '!J4 -> PO NO：Below list
H5: ='Invoice '!J5 -> PAYMENT TERMS: TT
B6: ='Invoice '!B6 -> TELL: 0755-29698989 | H6: ='Invoice '!J6 -> DELIVERY TERMS:C&F HAIPHONG
A7: BUYER: | H7: ='Invoice '!J7 -> PORT OF LOADING:SHEKOU
B8: ='Invoice '!B8 -> NAME: MOONPO DEVELOPMENT(VIETNAM) LIMITED | H8: ='Invoice '!J8 -> PORT OF DISCHARGE: HAIPHONG
B9: ='Invoice '!B9 -> ADDRESS: LOT CN-01, DONG VAN IV INDUSTRIAL ZONE, DAI CUONG WARD, KIM BANG TOWN, HA NAM PROVINCE, VIET NAM | H9: ='Invoice '!J9 -> PORT OF TRANSIT:
H10: ='Invoice '!J10 -> ETD POL:2025-04-28
B11: ='Invoice '!B11 -> TAX NUMBER: 0700834811 | H11: ='Invoice '!J11 -> ETA POD:2025-04-30
B12: ='Invoice '!B12 -> TELL:(+84) 0396869966, Email: vttdung@moonpo.com
A13: VESSEL/VOYAGE: BY OCEAN
A14: NO | B14: DESCRIPTIONS OF GOODS | F14: QUANTITY OF GOODS | G14: UNIT | H14: NO OF CARTON | I14: G/W (KG) | J14: N/W (KG) | K14: M3
B15: PO NO. | C15: PO Line No. | D15: PART NO | E15: DESC
A16: 1 | B16: 250302-1109 | C16: 1 | D16: B125-6.5A | E16: PROTECTION FILM | F16: 100 | G16: ROLL | H16: M1-M2 | I16: 58.13 | J16: 55
A17: 2 | B17: 250340-1115 | C17: 1 | D17: LT5GEO | E17: PCBA TESTING FIXTURE | F17: 1 | G17: PCS | H17: H1 | I17: 4.58 | J17: 4.08
A18: 3 | B18: 250340-1115 | C18: 2 | D18: AE-BRISA | E18: STICK BLOWING NOZZLE BOARD SPONGE FIXTURE | F18: 1 | G18: PCS | H18: H2 | I18: 13 | J18: 0.15
A19: 4 | B19: 250340-1115 | C19: 3 | D19: AE-BRISA | E19: FIXED NOZZLE ASSEMBLY RUBBER RING FIXTURE | F19: 1 | G19: PCS | H19: H2 | I19: 0 | J19: 0.23
A20: 5 | B20: 250340-1115 | C20: 4 | D20: AE-BRISA | E20: PRESSURE LEFT SHELL BEER MACHINE FIXTURE | F20: 1 | G20: PCS | H20: H2 | I20: 0 | J20: 1.4
A21: 6 | B21: 250340-1115 | C21: 5 | D21: AE-BRISA | E21: RIGHT SIDE SHELL BEER MACHINE FIXTURE | F21: 1 | G21: PCS | H21: H2 | I21: 0 | J21: 1.4
A22: 7 | B22: 250340-1115 | C22: 6 | D22: AE-BRISA | E22: BLOWING FIXTURE | F22: 1 | G22: PCS | H22: H2 | I22: 0 | J22: 8.6
A23: TOTAL: | F23: =SUM(F16:F22) -> 106 | I23: =SUM(I16:I22) -> 75.71 | J23: =SUM(J16:J22) -> 70.86
A24: NO OF PACKAGE: 4 PACKAGE ONLY
F25: MOONPO TRADING(SHENZHEN)CO.,LTD
