Workbook

Sheet MPVN2025072-25019
A1: PURCHASE ORDER
E2: PO NO:MPVN2025072-25019
E3: PO DATE: | F3: 45915
A4: BUYER: | B4: MOONPO DEVELOPMENT(VIETNAM) LIMITED
B5: ADDRESS: LOT CN-01，DONG VAN IV INDUSTRIAL ZONE,LE HO WARD,NINH BINH PROVINCE, VIETNAM
B6: TAX NO: 0700834811
B7: PIC: MR. YC WONG
A8: SELLER: | B8: MOONPO TRADING(SHENZHEN)CO.,LTD
B9: ADDRESS: 1F,NO.28 XIANGXING ROAD,BUYONG COMMUNITY,SHAJING STREET,BAO'AN DISTRICT,SHENZHEN CITY,CHINA.
A10: I. DESCRIPTIONS OF GOODS:BY OCEAN
A11: NO | B11: DESCRIPTION OF GOODS | D11: QUANTITY | E11: UNIT | F11: ORIGIN | G11: UNIT PRICE (USD) | H11: AMOUNT (USD)
B12: Part no | C12: DESC
A13: 1 | B13: 001-25019-01A | C13: PLASTIC TOOLING | D13: 1 | E13: SET | F13: CHINA | G13: 6288.3873 | H13: =G13*D13 -> 6288.3873
D14: =SUM(D13:D13) -> 1 | H14: =SUM(H13:H13) -> 6288.3873
B15: 1. Cargo is new 100%.
B16: 2. Delivery terms: C&F HAIPHONG
B17: 3. Delivery time: in DEC,2025
B18: 4. Shipping method: BY OCEAN
B19: 5. Packing standards: Following exporting standards
B20: 6. Payment terms: TT
B21: 7. PO has been acknowledged and signed by 02 parties and sent via email.
A22: ACCEPTED BY SELLER | E22: BUYER

Sheet 251139-1116
A1: PURCHASE ORDER
E2: PO NO:251139-1116
E3: PO DATE: | F3: 46000
A4: BUYER: | B4: MOONPO DEVELOPMENT(VIETNAM) LIMITED
B5: ADDRESS: LOT CN-01，DONG VAN IV INDUSTRIAL ZONE,LE HO WARD,NINH BINH PROVINCE, VIETNAM
B6: TAX NO: 0700834811
B7: PIC: MR. YC WONG
A8: SELLER: | B8: MOONPO TRADING(SHENZHEN)CO.,LTD
B9: ADDRESS: 1F,NO.28 XIANGXING ROAD,BUYONG COMMUNITY,SHAJING STREET,BAO'AN DISTRICT,SHENZHEN CITY,CHINA.
A10: I. DESCRIPTIONS OF GOODS:BY OCEAN
A11: NO | B11: DESCRIPTION OF GOODS | D11: QUANTITY | E11: UNIT | F11: ORIGIN | G11: UNIT PRICE (USD) | H11: AMOUNT (USD)
B12: Part no | C12: DESC
A13: 1 | B13: 001-25019-01A-01 | C13: ROBOT ARM | D13: 1 | E13: SET | F13: CHINA | G13: 54.0286 | H13: =G13*D13 -> 54.0286
D14: =SUM(D13:D13) -> 1 | H14: =SUM(H13:H13) -> 54.0286
B15: 1. Cargo is new 100%.
B16: 2. Delivery terms: C&F HAIPHONG
B17: 3. Delivery time: in DEC,2025
B18: 4. Shipping method: BY OCEAN
B19: 5. Packing standards: Following exporting standards
B20: 6. Payment terms: TT
B21: 7. PO has been acknowledged and signed by 02 parties and sent via email.
A22: ACCEPTED BY SELLER | E22: BUYER

Sheet 251046-1115
A1: PURCHASE ORDER
E2: PO NO:251046-1115
E3: PO DATE: | F3: 45974
A4: BUYER: | B4: MOONPO DEVELOPMENT(VIETNAM) LIMITED
B5: ADDRESS: LOT CN-01，DONG VAN IV INDUSTRIAL ZONE,LE HO WARD,NINH BINH PROVINCE, VIETNAM
B6: TAX NO: 0700834811
B7: PIC: MR. YC WONG
A8: SELLER: | B8: MOONPO TRADING(SHENZHEN)CO.,LTD
B9: ADDRESS: 1F,NO.28 XIANGXING ROAD,BUYONG COMMUNITY,SHAJING STREET,BAO'AN DISTRICT,SHENZHEN CITY,CHINA.
A10: I. DESCRIPTIONS OF GOODS:BY OCEAN
A11: NO | B11: DESCRIPTION OF GOODS | D11: QUANTITY | E11: UNIT | F11: ORIGIN | G11: UNIT PRICE (USD) | H11: AMOUNT (USD)
B12: Part no | C12: DESC
A13: 1 | B13: L=958mm | C13: LOWER HEATING PLATE | D13: 1 | E13: PCS | F13: CHINA | G13: 87.7965 | H13: =G13*D13 -> 87.7965
A14: 2 | B14: L=1030mm | C14: LOWER HEATING PLATE | D14: 6 | E14: PCS | F14: CHINA | G14: 87.7965 | H14: =G14*D14 -> 526.779
A15: 3 | B15: 4mm² | C15: HIGH TEMPERATURE WIRE | D15: 15 | E15: M | F15: CHINA | G15: 8.1043 | H15: =G15*D15 -> 121.5645
D16: =SUM(D13:D15) -> 22 | H16: =SUM(H13:H15) -> 736.14
B17: 1. Cargo is new 100%.
B18: 2. Delivery terms: C&F HAIPHONG
B19: 3. Delivery time: in DEC,2025
B20: 4. Shipping method: BY OCEAN
B21: 5. Packing standards: Following exporting standards
B22: 6. Payment terms: TT
B23: 7. PO has been acknowledged and signed by 02 parties and sent via email.
A24: ACCEPTED BY SELLER | E24: BUYER

Sheet 251143-1115
A1: PURCHASE ORDER
E2: PO NO:251143-1115
E3: PO DATE: | F3: 46000
A4: BUYER: | B4: MOONPO DEVELOPMENT(VIETNAM) LIMITED
B5: ADDRESS: LOT CN-01，DONG VAN IV INDUSTRIAL ZONE,LE HO WARD,NINH BINH PROVINCE, VIETNAM
B6: TAX NO: 0700834811
B7: PIC: MR. YC WONG
A8: SELLER: | B8: MOONPO TRADING(SHENZHEN)CO.,LTD
B9: ADDRESS: 1F,NO.28 XIANGXING ROAD,BUYONG COMMUNITY,SHAJING STREET,BAO'AN DISTRICT,SHENZHEN CITY,CHINA.
A10: I. DESCRIPTIONS OF GOODS:BY OCEAN
A11: NO | B11: DESCRIPTION OF GOODS | D11: QUANTITY | E11: UNIT | F11: ORIGIN | G11: UNIT PRICE (USD) | H11: AMOUNT (USD)
B12: Part no | C12: DESC
A13: 1 | B13: CROSS FIRE | C13: DRIVE THE HANDLE SCREW FIXTURE | D13: 4 | E13: PCS | F13: CHINA | G13: 10.8057 | H13: =G13*D13 -> 43.2228
A14: 2 | B14: CROSS FIRE | C14: DRILL THE FINISHED SCREW FIXTURE | D14: 4 | E14: PCS | F14: CHINA | G14: 8.1043 | H14: =G14*D14 -> 32.4172
A15: 3 | B15: CROSS FIRE | C15: BEER MARBLE FIXTURE | D15: 1 | E15: PCS | F15: CHINA | G15: 8.1043 | H15: =G15*D15 -> 8.1043
A16: 4 | B16: CROSS FIRE | C16: COUNTING FIXTURE | D16: 1 | E16: PCS | F16: CHINA | G16: 67.5357 | H16: =G16*D16 -> 67.5357
A17: 5 | B17: CROSS FIRE | C17: USE THE CONSOLE DATE FIXTURE | D17: 1 | E17: PCS | F17: CHINA | G17: 6.7536 | H17: =G17*D17 -> 6.7536
A18: 6 | B18: TRAVEL OPERATION | C18: POLISH THE PEN TIP FIXTURE | D18: 1 | E18: PCS | F18: CHINA | G18: 10.8057 | H18: =G18*D18 -> 10.8057
A19: 7 | B19: TRAVEL OPERATION | C19: WELDING FIXTURE | D19: 2 | E19: PCS | F19: CHINA | G19: 6.7536 | H19: =G19*D19 -> 13.5072
A20: 8 | B20: TRAVEL OPERATION | C20: WELDING PROBE LEAD FIXTURE | D20: 1 | E20: PCS | F20: CHINA | G20: 6.7536 | H20: =G20*D20 -> 6.7536
A21: 9 | B21: TRAVEL OPERATION | C21: PULL OUT THE PEN WIRE FIXTURE | D21: 1 | E21: PCS | F21: CHINA | G21: 40.5214 | H21: =G21*D21 -> 40.5214
A22: 10 | B22: TRAVEL OPERATION | C22: PANEL SEPARATION FIXTURE | D22: 1 | E22: PCS | F22: CHINA | G22: 6.7536 | H22: =G22*D22 -> 6.7536
A23: 11 | B23: TRAVEL OPERATION | C23: PRESS THE BATTERY CELL INTO THE SHELL FIXTURE | D23: 1 | E23: PCS | F23: CHINA | G23: 10.8057 | H23: =G23*D23 -> 10.8057
A24: 12 | B24: TRAVEL OPERATION | C24: PRESS THE BATTERY CELLS INTO THE FIXTURE | D24: 1 | E24: PCS | F24: CHINA | G24: 10.8057 | H24: =G24*D24 -> 10.8057
... A37: 25 | B37: 100-13002-02-01 V01 | C37: STENCIL | D37: 1 | E37: PCS | F37: CHINA | G37: 19.5854 | H37: =G37*D37 -> 19.5854
D38: =SUM(D13:D37) -> 40 | H38: =SUM(H13:H37) -> 738.1659
B39: 1. Cargo is new 100%.
B40: 2. Delivery terms: C&F HAIPHONG
B41: 3. Delivery time: in DEC,2025
B42: 4. Shipping method: BY OCEAN
B43: 5. Packing standards: Following exporting standards
B44: 6. Payment terms: TT
B45: 7. PO has been acknowledged and signed by 02 parties and sent via email.
A46: ACCEPTED BY SELLER | E46: BUYER

Sheet Invoice 
A1: COMMERCIAL INVOICE
A2: SELLER: | J2: INVOICE NO:MPT250084
B3: NAME:MOONPO TRADING(SHENZHEN)CO.,LTD | J3: INVOICE DATE:2025-12-11
B4: ADDRESS: 1F,NO.28 XIANGXING ROAD,BUYONG COMMUNITY,SHAJING STREET,BAO'AN DISTRICT,SHENZHEN CITY,CHINA. | J4: PO NO：Below list
J5: PAYMENT TERMS: TT
B6: TELL: 0755-29698989 | J6: DELIVERY TERMS:C&F HAIPHONG
A7: BUYER: | J7: PORT OF LOADING:SHEKOU
B8: NAME: MOONPO DEVELOPMENT(VIETNAM) LIMITED | J8: PORT OF DISCHARGE: HAIPHONG
B9: ADDRESS: LOT CN-01，DONG VAN IV INDUSTRIAL ZONE,LE HO WARD,NINH BINH PROVINCE, VIETNAM | J9: PORT OF TRANSIT:
J10: ETD POL:2025-12-18
B11: TAX NUMBER: 0700834811 | J11: ETA POD:2025-12-20
B12: TELL:(+84) 9885 16638, Email: ltlien@moonpo.com
A13: VESSEL/VOYAGE: BY OCEAN
A14: NO | B14: DESCRIPTIONS OF GOODS | G14: HS code | H14: ORIGIN OF GOODS | I14: QUANTITY | J14: UNIT | K14: UNIT PRICE (USD) | L14: AMOUNT (USD)
B15: PO NO. | C15: PO Line No. | D15: PART NO | E15: NAME | F15: DESC
A16: 1 | B16: MPVN2025072-25019 | C16: 1 | D16: 001-25019-01A | E16: 塑胶模具 | F16: PLASTIC TOOLING | G16: 84807190 | H16: CHINA | I16: 1 | J16: SET | K16: 6288.3873 | L16: =K16*I16 -> 6288.3873
A17: 2 | B17: 251139-1116 | C17: 7 | D17: 001-25019-01A-01 | E17: 模具机械手治具 | F17: ROBOT ARM | G17: 84779039 | H17: CHINA | I17: 1 | J17: SET | K17: 54.0286 | L17: =K17*I17 -> 54.0286
A18: 3 | B18: 251046-1115 | C18: 1 | D18: L=958mm | E18: 下层发热板 | F18: LOWER HEATING PLATE | G18: 85166090 | H18: CHINA | I18: 1 | J18: PCS | K18: 87.7965 | L18: =K18*I18 -> 87.7965
A19: 4 | B19: 251046-1115 | C19: 2 | D19: L=1030mm | E19: 上层发热板 | F19: LOWER HEATING PLATE | G19: 85166090 | H19: CHINA | I19: 6 | J19: PCS | K19: 87.7965 | L19: =K19*I19 -> 526.779
A20: 5 | B20: 251046-1115 | C20: 3 | D20: 4mm² | E20: 高温线 | F20: HIGH TEMPERATURE WIRE | G20: 85444929 | H20: CHINA | I20: 15 | J20: M | K20: 8.1043 | L20: =K20*I20 -> 121.5645
A21: 6 | B21: 251143-1115 | C21: 1 | D21: CROSS FIRE | E21: 打手柄螺丝治具 | F21: DRIVE THE HANDLE SCREW FIXTURE | G21: 84662090 | H21: CHINA | I21: 4 | J21: PCS | K21: 10.8057 | L21: =K21*I21 -> 43.2228
A22: 7 | B22: 251143-1115 | C22: 2 | D22: CROSS FIRE | E22: 打成品螺丝治具 | F22: DRILL THE FINISHED SCREW FIXTURE | G22: 84662090 | H22: CHINA | I22: 4 | J22: PCS | K22: 8.1043 | L22: =K22*I22 -> 32.4172
A23: 8 | B23: 251143-1115 | C23: 3 | D23: CROSS FIRE | E23: 啤弹珠治具 | F23: BEER MARBLE FIXTURE | G23: 84662090 | H23: CHINA | I23: 1 | J23: PCS | K23: 8.1043 | L23: =K23*I23 -> 8.1043
A24: 9 | B24: 251143-1115 | C24: 4 | D24: CROSS FIRE | E24: 计数治具 | F24: COUNTING FIXTURE | G24: 84662090 | H24: CHINA | I24: 1 | J24: PCS | K24: 67.5357 | L24: =K24*I24 -> 67.5357
A25: 10 | B25: 251143-1115 | C25: 5 | D25: CROSS FIRE | E25: 打主机日期治具 | F25: USE THE CONSOLE DATE FIXTURE | G25: 84662090 | H25: CHINA | I25: 1 | J25: PCS | K25: 6.7536 | L25: =K25*I25 -> 6.7536
A26: 11 | B26: 251143-1115 | C26: 6 | D26: TRAVEL OPERATION | E26: 打磨笔头治具 | F26: POLISH THE PEN TIP FIXTURE | G26: 84662090 | H26: CHINA | I26: 1 | J26: PCS | K26: 10.8057 | L26: =K26*I26 -> 10.8057
A27: 12 | B27: 251143-1115 | C27: 7 | D27: TRAVEL OPERATION | E27: 焊介子治具 | F27: WELDING FIXTURE | G27: 84662090 | H27: CHINA | I27: 2 | J27: PCS | K27: 6.7536 | L27: =K27*I27 -> 13.5072
... A45: 30 | B45: 251143-1115 | C45: 25 | D45: 100-13002-02-01 V01 | E45: 钢网 | F45: STENCIL | G45: 73144900 | H45: CHINA | I45: 1 | J45: PCS | K45: 19.5854 | L45: =K45*I45 -> 19.5854
A46: TOTAL: | I46: =SUM(I16:I45) -> 64 | L46: =SUM(L16:L45) -> 7816.7218
F48: MOONPO TRADING(SHENZHEN)CO.,LTD

Sheet Packing list 
A1: PACKING LIST
A2: SELLER: | H2: ='Invoice '!J2 -> INVOICE NO:MPT250084
B3: ='Invoice '!B3 -> NAME:MOONPO TRADING(SHENZHEN)CO.,LTD | H3: ='Invoice '!J3 -> INVOICE DATE:2025-12-11
B4: ADDRESS: 1F,NO.28 XIANGXING ROAD,BUYONG COMMUNITY,SHAJING STREET,BAO'AN DISTRICT,SHENZHEN CITY,CHINA. | H4: ='Invoice '!J4 -> PO NO：Below list
H5: ='Invoice '!J5 -> PAYMENT TERMS: TT
B6: ='Invoice '!B6 -> TELL: 0755-29698989 | H6: ='Invoice '!J6 -> DELIVERY TERMS:C&F HAIPHONG
A7: BUYER: | H7: ='Invoice '!J7 -> PORT OF LOADING:SHEKOU
B8: ='Invoice '!B8 -> NAME: MOONPO DEVELOPMENT(VIETNAM) LIMITED | H8: ='Invoice '!J8 -> PORT OF DISCHARGE: HAIPHONG
B9: ='Invoice '!B9 -> ADDRESS: LOT CN-01，DONG VAN IV INDUSTRIAL ZONE,LE HO WARD,NINH BINH PROVINCE, VIETNAM | H9: ='Invoice '!J9 -> PORT OF TRANSIT:
H10: ='Invoice '!J10 -> ETD POL:2025-12-18
B11: ='Invoice '!B11 -> TAX NUMBER: 0700834811 | H11: ='Invoice '!J11 -> ETA POD:2025-12-20
B12: ='Invoice '!B12 -> TELL:(+84) 9885 16638, Email: ltlien@moonpo.com
A13: VESSEL/VOYAGE: BY OCEAN
A14: NO | B14: DESCRIPTIONS OF GOODS | F14: QUANTITY OF GOODS | G14: UNIT | H14: NO OF CARTON | I14: G/W (KG) | J14: N/W (KG) | K14: M3
B15: PO NO. | C15: PO Line No. | D15: PART NO | E15: DESC
A16: 1 | B16: MPVN2025072-25019 | C16: 1 | D16: 001-25019-01A | E16: PLASTIC TOOLING | F16: 1 | G16: SET | H16: A01 | I16: 240 | J16: 237.51
A17: 2 | B17: 251139-1116 | C17: 7 | D17: 001-25019-01A-01 | E17: ROBOT ARM | F17: 1 | G17: SET | H17: A01 | I17: 0 | J17: 0.28
A18: 3 | B18: 251046-1115 | C18: 1 | D18: L=958mm | E18: LOWER HEATING PLATE | F18: 1 | G18: PCS | H18: B1 | I18: 18 | J18: 1.4
B19: 251046-1115 | C19: 2 | D19: L=1030mm | E19: LOWER HEATING PLATE | F19: 6 | G19: PCS | H19: B1 | I19: 0 | J19: 12
B20: 251046-1115 | C20: 3 | D20: 4mm² | E20: HIGH TEMPERATURE WIRE | F20: 15 | G20: M | H20: B1 | I20: 0 | J20: 1
B21: 251143-1115 | C21: 1 | D21: CROSS FIRE | E21: DRIVE THE HANDLE SCREW FIXTURE | F21: 4 | G21: PCS | H21: B2 | I21: 20.8 | J21: 1.92
B22: 251143-1115 | C22: 2 | D22: CROSS FIRE | E22: DRILL THE FINISHED SCREW FIXTURE | F22: 4 | G22: PCS | H22: B2 | I22: 0 | J22: 5.72
B23: 251143-1115 | C23: 3 | D23: CROSS FIRE | E23: BEER MARBLE FIXTURE | F23: 1 | G23: PCS | H23: B2 | I23: 0 | J23: 0.42
B24: 251143-1115 | C24: 4 | D24: CROSS FIRE | E24: COUNTING FIXTURE | F24: 1 | G24: PCS | H24: B2 | I24: 0 | J24: 6.86
B25: 251143-1115 | C25: 5 | D25: CROSS FIRE | E25: USE THE CONSOLE DATE FIXTURE | F25: 1 | G25: PCS | H25: B2 | I25: 0 | J25: 1.04
B26: 251143-1115 | C26: 6 | D26: TRAVEL OPERATION | E26: POLISH THE PEN TIP FIXTURE | F26: 1 | G26: PCS | H26: B2 | I26: 0 | J26: 0.7
B27: 251143-1115 | C27: 7 | D27: TRAVEL OPERATION | E27: WELDING FIXTURE | F27: 2 | G27: PCS | H27: B2 | I27: 0 | J27: 1
B28: 251143-1115 | C28: 8 | D28: TRAVEL OPERATION | E28: WELDING PROBE LEAD FIXTURE | F28: 1 | G28: PCS | H28: B2 | I28: 0 | J28: 0.1
B29: 251143-1115 | C29: 9 | D29: TRAVEL OPERATION | E29: PULL OUT THE PEN WIRE FIXTURE | F29: 1 | G29: PCS | H29: B2 | I29: 0 | J29: 2.54
B30: 251143-1115 | C30: 10 | D30: TRAVEL OPERATION | E30: PANEL SEPARATION FIXTURE | F30: 1 | G30: PCS | H30: B3 | I30: 18.5 | J30: 0.4
... B40: 251143-1115 | C40: 20 | D40: TRAVEL OPERATION | E40: SCREWDRIVER FIXTURES FOR PCB BOARDS | F40: 3 | G40: PCS | H40: B3 | I40: 0 | J40: 1.29
B41: 251143-1115 | C41: 21 | D41: TRAVEL OPERATION | E41: SCREW MACHINE SCREW FIXTURE FOR THE MAIN MACHINE | F41: ~ | G41: PCS | H41: B3 | I41: 0 | J41: 2.56
B42: 251143-1115 | C42: 22 | D42: TRAVEL OPERATION | E42: MARK THE DATE OF THE MAIN UNIT AND THE BATTERY DOOR FIXTURE | F42: 1 | G42: PCS | H42: B3 | I42: 0 | J42: 0.43
B43: 251143-1115 | C43: 23 | D43: TRAVEL OPERATION | E43: PUNCHING BOX HOLE FIXTURE | F43: 1 | G43: PCS | H43: B3 | I43: 0 | J43: 3.68
B44: 251143-1115 | C44: 24 | D44: Operation Bluey | E44: BIAXIAL STRETCHING COLUMN FIXTURE | F44: 3 | G44: PCS | H44: B4 | I44: 21.61 | J44: 20.61
A45: 4 | B45: 251143-1115 | C45: 25 | D45: 100-13002-02-01 V01 | E45: STENCIL | F45: 1 | G45: PCS | H45: B5 | I45: 1.1 | J45: 0.6
A46: TOTAL: | F46: =SUM(F16:F45) -> 62 | I46: =SUM(I16:I45) -> 320.01 | J46: =SUM(J16:J45) -> 311.36
A47: NO OF PACKAGE:6 PACKAGE ONLY
E48: ~ | F48: MOONPO TRADING(SHENZHEN)CO.,LTD
